statistical_plot/__init__.py
statistical_plot/barplot.py
statistical_plot-0.10.dist-info/LICENSE.md
statistical_plot-0.10.dist-info/METADATA
statistical_plot-0.10.dist-info/WHEEL
statistical_plot-0.10.dist-info/top_level.txt
statistical_plot-0.10.dist-info/RECORD
