Metadata-Version: 2.1
Name: statistical-plot
Version: 0.10
Summary: Statistical plotting with good aesthetics.
Home-page: https://github.com/ChenLiu-1996/StatsPlot
Author: Chen Liu
Author-email: chen.liu.cl2482@yale.edu
License: MIT
Keywords: plotting,plot,statistical plotting,statistical plot
Classifier: Development Status :: 3 - Alpha
Classifier: Intended Audience :: Developers
Classifier: License :: OSI Approved :: MIT License
Classifier: Programming Language :: Python :: 3
License-File: LICENSE.md
Requires-Dist: numpy
Requires-Dist: pandas
Requires-Dist: seaborn
Requires-Dist: matplotlib
